qt_binder/__init__.py
qt_binder/api.py
qt_binder/binder.py
qt_binder/binding.py
qt_binder/bound_editor.py
qt_binder/constants.py
qt_binder/loopback_guard.py
qt_binder/raw_widgets.py
qt_binder/testing.py
qt_binder/type_registry.py
qt_binder/widgets.py
qt_binder/qt/QtCore.py
qt_binder/qt/QtGui.py
qt_binder/qt/QtNetwork.py
qt_binder/qt/QtOpenGL.py
qt_binder/qt/QtScript.py
qt_binder/qt/QtSvg.py
qt_binder/qt/QtTest.py
qt_binder/qt/QtWebKit.py
qt_binder/qt/__init__.py
qt_binder/qt/ui_loader.py
qt_binder/tests/__init__.py
qt_binder/tests/dummies.py
qt_binder/tests/form.ui
qt_binder/tests/test_binder.py
qt_binder/tests/test_binding.py
qt_binder/tests/test_lazy_registry.py
qt_binder/tests/test_loopback_guard.py
qt_binder/tests/test_raw_widgets.py
qt_binder/tests/test_type_registry.py
qt_binder/tests/test_ui_loader.py
qt_binder/tests/test_widgets.py
qt_binder-0.4.dist-info/LICENSE.txt
qt_binder-0.4.dist-info/METADATA
qt_binder-0.4.dist-info/WHEEL
qt_binder-0.4.dist-info/top_level.txt
qt_binder-0.4.dist-info/RECORD
